apilgtm/__init__.py
apilgtm/clean_url.py
apilgtm/configs/constants.py
apilgtm/configs/tlds.py
apilgtm/helpers/__init__.py
apilgtm/helpers/evaluate.py
apilgtm/helpers/sanitize.py
apilgtm/utils/__init__.py
apilgtm/utils/err.py
apilgtm/utils/tld.py
apilgtm/utils/url.py
apilgtm/utils/ver.py
apilgtm-1.0.0.dist-info/licenses/LICENSE
apilgtm-1.0.0.dist-info/METADATA
apilgtm-1.0.0.dist-info/WHEEL
apilgtm-1.0.0.dist-info/top_level.txt
apilgtm-1.0.0.dist-info/RECORD
