Metadata-Version: 2.4
Name: apilgtm
Version: 1.0.0
Author-email: developers <developers@tagdots.com>
Project-URL: Changelog, https://github.com/tagdots/apilgtm/blob/main/CHANGELOG.md
Project-URL: Documentation, https://github.com/tagdots/apilgtm/blob/main/README.md
Project-URL: Homepage, https://github.com/tagdots
Project-URL: Issues, https://github.com/tagdots/apilgtm/issues
Project-URL: Repository, https://github.com/tagdots/apilgtm
Classifier: Intended Audience :: Developers
Classifier: Programming Language :: Python :: 3 :: Only
Classifier: Programming Language :: Python :: 3.12
Classifier: Programming Language :: Python :: 3.13
Classifier: Programming Language :: Python :: 3.14
Classifier: Topic :: Software Development :: Build Tools
Requires-Python: >=3.12.10
License-File: LICENSE
Provides-Extra: local
Requires-Dist: commitizen; extra == "local"
Requires-Dist: pre-commit; extra == "local"
Provides-Extra: test
Requires-Dist: build; extra == "test"
Requires-Dist: coverage; extra == "test"
Requires-Dist: flake8; extra == "test"
Requires-Dist: isort; extra == "test"
Requires-Dist: pyscan-rs; extra == "test"
Requires-Dist: pytest; extra == "test"
Requires-Dist: twine; extra == "test"
Dynamic: license-file
